discordgpt/__init__.py
discordgpt-0.1.1.dist-info/LICENSE
discordgpt-0.1.1.dist-info/METADATA
discordgpt-0.1.1.dist-info/WHEEL
discordgpt-0.1.1.dist-info/top_level.txt
discordgpt-0.1.1.dist-info/RECORD
