Metadata-Version: 2.1
Name: discordgpt
Version: 0.1.1
Summary: A package for making a Discord ChatGPT bot
Author: Aljo
License: MIT License
Project-URL: Homepage, https://github.com/Aljoberg/DiscordGPT
Project-URL: Repository, https://github.com/Aljoberg/DiscordGPT
Keywords: ChatGPT,Discord,bot,openai
Classifier: Development Status :: 5 - Production/Stable
Classifier: Environment :: Console
Classifier: License :: OSI Approved :: MIT License
Classifier: Programming Language :: Python :: 3
Classifier: Topic :: Communications :: Chat
Classifier: Topic :: Scientific/Engineering :: Artificial Intelligence
License-File: LICENSE
Requires-Dist: openai
Requires-Dist: discord.py
Requires-Dist: colorama
